cicspi/__init__.py
cicspi/device.py
cicspi/entry.py
cicspi/spiceobject.py
cicspi/spiceparser.py
cicspi/subckt.py
cicspi/subcktinstance.py
cicspi-0.1.2.dist-info/METADATA
cicspi-0.1.2.dist-info/WHEEL
cicspi-0.1.2.dist-info/entry_points.txt
cicspi-0.1.2.dist-info/top_level.txt
cicspi-0.1.2.dist-info/RECORD
