Metadata-Version: 2.4
Name: cicspi
Version: 0.1.2
Summary: Spice toolbox
Home-page: https://github.com/wulffern/cicspi
Author: Carsten Wulff
Author-email: Carsten Wulff <carsten@wulff.no>
License: MIT
Project-URL: Homepage, https://github.com/wulffern/cicspi
Project-URL: Bug Tracker, https://github.com/wulffern/cicspi/issues
Classifier: Programming Language :: Python :: 3
Classifier: Operating System :: OS Independent
Requires-Python: >=3.8
Requires-Dist: click
Dynamic: author
Dynamic: home-page
Dynamic: requires-python
